{
	"format_version": "1.21.11",
	"credit": "Made with Blockbench",
	"parent": "minecraft:block/tinted_cross",
	"textures": {
		"cross": "block/fern"
	},
	"elements": [
		{
			"from": [5.51642, 2.62875, 0.20541],
			"to": [13.51642, 2.62875, 8.20541],
			"rotation": {"x": 41.10725, "y": 9.53783, "z": 25.64818, "origin": [8.51642, 2.62875, 3.20541]},
			"faces": {
				"up": {"uv": [2.75, 2.75, 13, 13.25], "texture": "#cross"},
				"down": {"uv": [2.75, 13.25, 13, 2.75], "texture": "#cross"}
			}
		},
		{
			"from": [6.86093, 3.45103, 7.04512],
			"to": [14.86093, 3.45103, 15.04512],
			"rotation": {"x": -109.78705, "y": -20.23452, "z": 131.74233, "origin": [9.86093, 3.45103, 10.04512]},
			"faces": {
				"up": {"uv": [2.75, 2.75, 13, 13.25], "texture": "#cross"},
				"down": {"uv": [2.75, 13.25, 13, 2.75], "texture": "#cross"}
			}
		},
		{
			"from": [10.09127, 0.73572, 2.99288],
			"to": [18.09127, 0.73572, 10.99288],
			"rotation": {"x": -1.1084, "y": -44.87598, "z": 22.58376, "origin": [13.09127, 0.73572, 5.99288]},
			"faces": {
				"up": {"uv": [2.75, 2.75, 13, 13.25], "texture": "#cross"},
				"down": {"uv": [2.75, 13.25, 13, 2.75], "texture": "#cross"}
			}
		},
		{
			"from": [8.21733, 2.96544, 2.42526],
			"to": [16.21733, 2.96544, 10.42526],
			"rotation": {"x": -34.97591, "y": -30.66649, "z": 83.41996, "origin": [11.21733, 2.96544, 5.42526]},
			"faces": {
				"up": {"uv": [13.25, 2.75, 2.75, 13], "rotation": 90, "texture": "#cross"},
				"down": {"uv": [2.75, 2.75, 13.25, 13], "rotation": 90, "texture": "#cross"}
			}
		},
		{
			"from": [1.08461, 3.02905, 5.3181],
			"to": [9.08461, 3.02905, 13.3181],
			"rotation": {"x": -170.31962, "y": 49.70383, "z": 138.99487, "origin": [4.08461, 3.02905, 8.3181]},
			"faces": {
				"up": {"uv": [2.75, 2.75, 13, 13.25], "texture": "#cross"},
				"down": {"uv": [2.75, 13.25, 13, 2.75], "texture": "#cross"}
			}
		},
		{
			"from": [6.32932, -0.89454, 0.90065],
			"to": [14.32932, -0.89454, 8.90065],
			"rotation": {"x": 91.04521, "y": 59.89074, "z": 58.311, "origin": [8.5702, 1.18341, 6.92806]},
			"faces": {
				"up": {"uv": [2.75, 2.75, 13, 13.25], "texture": "#cross"},
				"down": {"uv": [2.75, 13.25, 13, 2.75], "texture": "#cross"}
			}
		},
		{
			"from": [6.72943, -0.92872, 1.24777],
			"to": [14.72943, -0.92872, 9.24777],
			"rotation": {"x": -38.87293, "y": -45.54587, "z": 88.49993, "origin": [8.5702, 1.18341, 6.92806]},
			"faces": {
				"up": {"uv": [2.75, 2.75, 13, 13.25], "texture": "#cross"},
				"down": {"uv": [2.75, 13.25, 13, 2.75], "texture": "#cross"}
			}
		},
		{
			"from": [7.05809, -1.74518, 0.46724],
			"to": [15.05809, -1.74518, 8.46724],
			"rotation": {"x": -134.59449, "y": -4.63083, "z": 154.80298, "origin": [8.5702, 1.18341, 6.92806]},
			"faces": {
				"up": {"uv": [2.75, 2.75, 13, 13.25], "texture": "#cross"},
				"down": {"uv": [2.75, 13.25, 13, 2.75], "texture": "#cross"}
			}
		},
		{
			"from": [7.4745, -1.82674, 0.65344],
			"to": [15.4745, -1.82674, 8.65344],
			"rotation": {"x": 19.51641, "y": 14.74813, "z": 16.34445, "origin": [8.5702, 1.18341, 6.92806]},
			"faces": {
				"up": {"uv": [2.75, 2.75, 13, 13.25], "texture": "#cross", "cullface": "down"},
				"down": {"uv": [2.75, 13.25, 13, 2.75], "texture": "#cross", "cullface": "down"}
			}
		},
		{
			"from": [5.73286, 0.15889, 0.96138],
			"to": [13.73286, 0.15889, 8.96138],
			"rotation": {"x": 28.02211, "y": -8.51576, "z": 59.76988, "origin": [8.5702, 1.18341, 6.92806]},
			"faces": {
				"up": {"uv": [13.25, 2.75, 2.75, 13], "rotation": 90, "texture": "#cross"},
				"down": {"uv": [2.75, 2.75, 13.25, 13], "rotation": 90, "texture": "#cross"}
			}
		},
		{
			"from": [6.17989, 3.40245, 2.77767],
			"to": [12.17989, 3.40245, 8.77767],
			"rotation": {"x": 41.10725, "y": 9.53783, "z": 25.64818, "origin": [8.17989, 3.40245, 4.77767]},
			"faces": {
				"up": {"uv": [2.75, 2.75, 13, 13.25], "texture": "#cross"},
				"down": {"uv": [2.75, 13.25, 13, 2.75], "texture": "#cross"}
			}
		},
		{
			"from": [7.86093, 3.95103, 8.04512],
			"to": [13.86093, 3.95103, 14.04512],
			"rotation": {"x": -109.78705, "y": -20.23452, "z": 131.74233, "origin": [9.86093, 3.95103, 10.04512]},
			"faces": {
				"up": {"uv": [2.75, 2.75, 13, 13.25], "texture": "#cross"},
				"down": {"uv": [2.75, 13.25, 13, 2.75], "texture": "#cross"}
			}
		},
		{
			"from": [6.39391, 4.84417, 5.8919],
			"to": [12.39391, 4.84417, 11.8919],
			"rotation": {"x": 67.18483, "y": -33.46711, "z": 29.2064, "origin": [8.39391, 4.84417, 7.8919]},
			"faces": {
				"up": {"uv": [2.75, 2.75, 13, 13.25], "texture": "#cross"},
				"down": {"uv": [2.75, 13.25, 13, 2.75], "texture": "#cross"}
			}
		},
		{
			"from": [8.65747, 3.50138, 4.28334],
			"to": [14.65747, 3.50138, 10.28334],
			"rotation": {"x": -34.97591, "y": -30.66649, "z": 83.41996, "origin": [10.65747, 3.50138, 6.28334]},
			"faces": {
				"up": {"uv": [13.25, 2.75, 2.75, 13], "rotation": 90, "texture": "#cross"},
				"down": {"uv": [2.75, 2.75, 13.25, 13], "rotation": 90, "texture": "#cross"}
			}
		},
		{
			"from": [3.18508, 3.72371, 7.10678],
			"to": [9.18508, 3.72371, 13.10678],
			"rotation": {"x": -170.31962, "y": 49.70383, "z": 138.99487, "origin": [5.18508, 3.72371, 9.10678]},
			"faces": {
				"up": {"uv": [2.75, 2.75, 13, 13.25], "texture": "#cross"},
				"down": {"uv": [2.75, 13.25, 13, 2.75], "texture": "#cross"}
			}
		},
		{
			"from": [7.23281, 0.87916, 3.03175],
			"to": [13.23281, 0.87916, 9.03175],
			"rotation": {"x": 91.04521, "y": 59.89074, "z": 58.311, "origin": [8.47369, 2.95711, 8.05916]},
			"faces": {
				"up": {"uv": [2.75, 2.75, 13, 13.25], "texture": "#cross"},
				"down": {"uv": [2.75, 13.25, 13, 2.75], "texture": "#cross"}
			}
		},
		{
			"from": [6.3937, 0.57128, 2.35438],
			"to": [12.3937, 0.57128, 8.35438],
			"rotation": {"x": -38.87293, "y": -45.54587, "z": 88.49993, "origin": [7.23447, 2.68341, 7.03467]},
			"faces": {
				"up": {"uv": [2.75, 2.75, 13, 13.25], "texture": "#cross"},
				"down": {"uv": [2.75, 13.25, 13, 2.75], "texture": "#cross"}
			}
		},
		{
			"from": [7.93028, -0.05033, 0.96208],
			"to": [13.93028, -0.05033, 6.96208],
			"rotation": {"x": -134.59449, "y": -4.63083, "z": 154.80298, "origin": [8.44239, 2.87826, 6.4229]},
			"faces": {
				"up": {"uv": [2.75, 2.75, 13, 13.25], "texture": "#cross"},
				"down": {"uv": [2.75, 13.25, 13, 2.75], "texture": "#cross"}
			}
		},
		{
			"from": [7.82122, -0.20095, 4.74538],
			"to": [13.82122, -0.20095, 10.74538],
			"rotation": {"x": 54.51641, "y": 14.74813, "z": 16.34445, "origin": [7.91692, 2.8092, 10.02]},
			"faces": {
				"up": {"uv": [2.75, 2.75, 13, 13.25], "texture": "#cross"},
				"down": {"uv": [2.75, 13.25, 13, 2.75], "texture": "#cross"}
			}
		},
		{
			"from": [6.53867, -0.09743, 2.85517],
			"to": [12.53867, -0.09743, 8.85517],
			"rotation": {"x": 28.02211, "y": -8.51576, "z": 59.76988, "origin": [7.15703, 1.43071, 9.08231]},
			"faces": {
				"up": {"uv": [13.25, 2.75, 2.75, 13], "rotation": 90, "texture": "#cross"},
				"down": {"uv": [2.75, 2.75, 13.25, 13], "rotation": 90, "texture": "#cross"}
			}
		}
	]
}